llm_api_adapter/__init__.py
llm_api_adapter/universal_adapter.py
llm_api_adapter/adapters/__init__.py
llm_api_adapter/adapters/anthropic_adapter.py
llm_api_adapter/adapters/base_adapter.py
llm_api_adapter/adapters/google_adapter.py
llm_api_adapter/adapters/openai_adapter.py
llm_api_adapter/errors/__init__.py
llm_api_adapter/errors/config_errors.py
llm_api_adapter/errors/llm_api_error.py
llm_api_adapter/llm_registry/__init__.py
llm_api_adapter/llm_registry/llm_registry.json
llm_api_adapter/llm_registry/llm_registry.py
llm_api_adapter/llms/__init__.py
llm_api_adapter/llms/anthropic/__init__.py
llm_api_adapter/llms/anthropic/sync_client.py
llm_api_adapter/llms/google/__init__.py
llm_api_adapter/llms/google/sync_client.py
llm_api_adapter/llms/openai/__init__.py
llm_api_adapter/llms/openai/sync_client.py
llm_api_adapter/models/__init__.py
llm_api_adapter/models/messages/__init__.py
llm_api_adapter/models/messages/chat_message.py
llm_api_adapter/models/responses/__init__.py
llm_api_adapter/models/responses/chat_response.py
llm_api_adapter-0.2.3.dist-info/licenses/LICENSE
llm_api_adapter-0.2.3.dist-info/METADATA
llm_api_adapter-0.2.3.dist-info/WHEEL
llm_api_adapter-0.2.3.dist-info/top_level.txt
llm_api_adapter-0.2.3.dist-info/RECORD
