Metadata-Version: 2.4
Name: llm-api-adapter
Version: 0.2.3
Summary: Lightweight, pluggable adapter for multiple LLM APIs (OpenAI, Anthropic, Google)
Author: Sergey Inozemtsev
License: MIT License
Project-URL: Repository, https://github.com/Inozem/llm_api_adapter/
Keywords: llm,adapter,lightweight,api
Classifier: Programming Language :: Python :: 3
Classifier: Programming Language :: Python :: 3.9
Classifier: Typing :: Typed
Classifier: License :: OSI Approved :: MIT License
Classifier: Operating System :: OS Independent
Requires-Python: >=3.9
License-File: LICENSE
Requires-Dist: requests>=2.32
Dynamic: license-file
